halo_video/__init__.py
halo_video/cli.py
halo_video/config_manager.py
halo_video/context_cache.py
halo_video/gemini_batch_predictor.py
halo_video/post_install.py
halo_video/transcript_utils.py
halo_video-1.0.8.dist-info/licenses/LICENSE
halo_video-1.0.8.dist-info/licenses/LICENSE_DETAILED.md
halo_video-1.0.8.dist-info/METADATA
halo_video-1.0.8.dist-info/WHEEL
halo_video-1.0.8.dist-info/entry_points.txt
halo_video-1.0.8.dist-info/top_level.txt
halo_video-1.0.8.dist-info/RECORD
