Metadata-Version: 2.4
Name: halo-video
Version: 1.0.8
Summary: Interactive Video QA System - AI-powered YouTube video analysis with question-answering capabilities using Google Gemini Vision API and audio transcription.
Author-email: Jeet Dekivadia <jeet.university@gmail.com>
Maintainer-email: Jeet Dekivadia <jeet.university@gmail.com>
License: MIT License
Project-URL: Homepage, https://github.com/jeet-dekivadia/google-deepmind
Project-URL: Repository, https://github.com/jeet-dekivadia/google-deepmind
Project-URL: Source Code, https://github.com/jeet-dekivadia/google-deepmind/tree/main/halo_video
Project-URL: Documentation, https://github.com/jeet-dekivadia/google-deepmind#halo-video
Project-URL: Bug Tracker, https://github.com/jeet-dekivadia/google-deepmind/issues
Project-URL: Google Summer of Code, https://summerofcode.withgoogle.com/
Project-URL: Google DeepMind, https://deepmind.google/
Keywords: ai,video-analysis,youtube,gemini,google-deepmind,google-summer-of-code,gsoc,halo,hierarchical-abstraction,longform-optimization,video-qa,multimodal,vision,cli,ffmpeg,transcription,machine-learning,artificial-intelligence
Classifier: Development Status :: 5 - Production/Stable
Classifier: Intended Audience :: Developers
Classifier: Intended Audience :: End Users/Desktop
Classifier: Operating System :: OS Independent
Classifier: Programming Language :: Python :: 3
Classifier: Programming Language :: Python :: 3.8
Classifier: Programming Language :: Python :: 3.9
Classifier: Programming Language :: Python :: 3.10
Classifier: Programming Language :: Python :: 3.11
Classifier: Programming Language :: Python :: 3.12
Classifier: Topic :: Multimedia :: Video
Classifier: Topic :: Scientific/Engineering :: Artificial Intelligence
Classifier: Topic :: Software Development :: Libraries :: Python Modules
Requires-Python: >=3.8
License-File: LICENSE
License-File: LICENSE_DETAILED.md
Requires-Dist: google-generativeai>=0.3.0
Requires-Dist: openai-whisper>=20231117
Requires-Dist: Pillow>=10.0.0
Requires-Dist: yt-dlp>=2024.4.9
Requires-Dist: ffmpeg-python>=0.2.0
Requires-Dist: rich>=13.7.0
Requires-Dist: httpx>=0.27.0
Requires-Dist: aiosqlite>=0.19.0
Requires-Dist: sentence-transformers>=2.7.0
Requires-Dist: imageio-ffmpeg>=0.4.8
Requires-Dist: click>=8.0.0
Provides-Extra: dev
Requires-Dist: pytest>=7.4.0; extra == "dev"
Requires-Dist: black>=23.0.0; extra == "dev"
Requires-Dist: flake8>=6.0.0; extra == "dev"
Requires-Dist: mypy>=1.5.0; extra == "dev"
Dynamic: license-file
